<?xml version="1.0"?>
<testResults>
  <FitNesseVersion>v20180127</FitNesseVersion>
  <rootPath>FrontPage.TestFixture</rootPath>
    <result>
    <counts>
      <right></right>
      <wrong></wrong>
      <ignores></ignores>
      <exceptions></exceptions>
    </counts>
    <date>2018-12-20T18:17:57-08:00</date>
    <runTimeInMillis>$result.runTimeInMillis</runTimeInMillis>
    <content>&lt;br/&gt;&lt;span class="meta"&gt;classpath: C:\eclipse-workspace\configAutomation\target\classes&lt;/span&gt;&lt;br/&gt;&lt;br/&gt;&lt;div class="collapsible closed"&gt;&lt;ul&gt;&lt;li&gt;&lt;a href='#' class='expandall'&gt;Expand&lt;/a&gt;&lt;/li&gt;&lt;li&gt;&lt;a href='#' class='collapseall'&gt;Collapse&lt;/a&gt;&lt;/li&gt;&lt;/ul&gt;
	&lt;p class="title"&gt;paths&lt;/p&gt;
	&lt;div&gt;&lt;br/&gt;&lt;span class="meta"&gt;variable defined: TEST_SYSTEM=slim&lt;/span&gt;
&lt;br/&gt;&lt;span class="meta"&gt;classpath: C:\baseline&lt;/span&gt;&lt;br/&gt;&lt;span class="meta"&gt;classpath: C:\Program Files\Java\jre1.8.0_161\lib\resources.jar&lt;/span&gt;&lt;br/&gt;&lt;span class="meta"&gt;classpath: C:\Program Files\Java\jre1.8.0_161\lib\rt.jar&lt;/span&gt;&lt;br/&gt;&lt;span class="meta"&gt;classpath: C:\Program Files\Java\jre1.8.0_161\lib\jsse.jar&lt;/span&gt;&lt;br/&gt;&lt;span class="meta"&gt;classpath: C:\Program Files\Java\jre1.8.0_161\lib\jce.jar&lt;/span&gt;&lt;br/&gt;&lt;span class="meta"&gt;classpath: C:\Program Files\Java\jre1.8.0_161\lib\charsets.jar&lt;/span&gt;&lt;br/&gt;&lt;span class="meta"&gt;classpath: C:\Program Files\Java\jre1.8.0_161\lib\jfr.jar&lt;/span&gt;&lt;br/&gt;&lt;span class="meta"&gt;classpath: C:\Program Files\Java\jre1.8.0_161\lib\ext\access-bridge-64.jar&lt;/span&gt;&lt;br/&gt;&lt;span class="meta"&gt;classpath: C:\Program Files\Java\jre1.8.0_161\lib\ext\cldrdata.jar&lt;/span&gt;&lt;br/&gt;&lt;span class="meta"&gt;classpath: C:\Program Files\Java\jre1.8.0_161\lib\ext\dnsns.jar&lt;/span&gt;&lt;br/&gt;&lt;span class="meta"&gt;classpath: C:\Program Files\Java\jre1.8.0_161\lib\ext\jaccess.jar&lt;/span&gt;&lt;br/&gt;&lt;span class="meta"&gt;classpath: C:\Program Files\Java\jre1.8.0_161\lib\ext\jfxrt.jar&lt;/span&gt;&lt;br/&gt;&lt;span class="meta"&gt;classpath: C:\Program Files\Java\jre1.8.0_161\lib\ext\localedata.jar&lt;/span&gt;&lt;br/&gt;&lt;span class="meta"&gt;classpath: C:\Program Files\Java\jre1.8.0_161\lib\ext\nashorn.jar&lt;/span&gt;&lt;br/&gt;&lt;span class="meta"&gt;classpath: C:\Program Files\Java\jre1.8.0_161\lib\ext\sunec.jar&lt;/span&gt;&lt;br/&gt;&lt;span class="meta"&gt;classpath: C:\Program Files\Java\jre1.8.0_161\lib\ext\sunjce_provider.jar&lt;/span&gt;&lt;br/&gt;&lt;span class="meta"&gt;classpath: C:\Program Files\Java\jre1.8.0_161\lib\ext\sunmscapi.jar&lt;/span&gt;&lt;br/&gt;&lt;span class="meta"&gt;classpath: C:\Program Files\Java\jre1.8.0_161\lib\ext\sunpkcs11.jar&lt;/span&gt;&lt;br/&gt;&lt;span class="meta"&gt;classpath: C:\Program Files\Java\jre1.8.0_161\lib\ext\zipfs.jar&lt;/span&gt;&lt;br/&gt;&lt;span class="meta"&gt;classpath: C:\Users\gaguilar\.m2\repository\org\seleniumhq\selenium\selenium-java\3.14.0\selenium-java-3.14.0.jar&lt;/span&gt;&lt;br/&gt;&lt;span class="meta"&gt;classpath: C:\Users\gaguilar\.m2\repository\org\seleniumhq\selenium\selenium-api\3.14.0\selenium-api-3.14.0.jar&lt;/span&gt;&lt;br/&gt;&lt;span class="meta"&gt;classpath: C:\Users\gaguilar\.m2\repository\org\seleniumhq\selenium\selenium-edge-driver\3.14.0\selenium-edge-driver-3.14.0.jar&lt;/span&gt;&lt;br/&gt;&lt;span class="meta"&gt;classpath: C:\Users\gaguilar\.m2\repository\org\seleniumhq\selenium\selenium-firefox-driver\3.14.0\selenium-firefox-driver-3.14.0.jar&lt;/span&gt;&lt;br/&gt;&lt;span class="meta"&gt;classpath: C:\Users\gaguilar\.m2\repository\org\seleniumhq\selenium\selenium-ie-driver\3.14.0\selenium-ie-driver-3.14.0.jar&lt;/span&gt;&lt;br/&gt;&lt;span class="meta"&gt;classpath: C:\Users\gaguilar\.m2\repository\org\seleniumhq\selenium\selenium-opera-driver\3.14.0\selenium-opera-driver-3.14.0.jar&lt;/span&gt;&lt;br/&gt;&lt;span class="meta"&gt;classpath: C:\Users\gaguilar\.m2\repository\org\seleniumhq\selenium\selenium-remote-driver\3.14.0\selenium-remote-driver-3.14.0.jar&lt;/span&gt;&lt;br/&gt;&lt;span class="meta"&gt;classpath: C:\Users\gaguilar\.m2\repository\org\seleniumhq\selenium\selenium-safari-driver\3.14.0\selenium-safari-driver-3.14.0.jar&lt;/span&gt;&lt;br/&gt;&lt;span class="meta"&gt;classpath: C:\Users\gaguilar\.m2\repository\org\seleniumhq\selenium\selenium-support\3.14.0\selenium-support-3.14.0.jar&lt;/span&gt;&lt;br/&gt;&lt;span class="meta"&gt;classpath: C:\Users\gaguilar\.m2\repository\org\seleniumhq\selenium\selenium-chrome-driver\3.14.0\selenium-chrome-driver-3.14.0.jar&lt;/span&gt;&lt;br/&gt;&lt;span class="meta"&gt;classpath: C:\Users\gaguilar\.m2\repository\net\bytebuddy\byte-buddy\1.8.3\byte-buddy-1.8.3.jar&lt;/span&gt;&lt;br/&gt;&lt;span class="meta"&gt;classpath: C:\Users\gaguilar\.m2\repository\org\apache\commons\commons-exec\1.3\commons-exec-1.3.jar&lt;/span&gt;&lt;br/&gt;&lt;span class="meta"&gt;classpath: C:\Users\gaguilar\.m2\repository\commons-codec\commons-codec\1.10\commons-codec-1.10.jar&lt;/span&gt;&lt;br/&gt;&lt;span class="meta"&gt;classpath: C:\Users\gaguilar\.m2\repository\commons-logging\commons-logging\1.2\commons-logging-1.2.jar&lt;/span&gt;&lt;br/&gt;&lt;span class="meta"&gt;classpath: C:\Users\gaguilar\.m2\repository\org\apache\httpcomponents\httpclient\4.5.5\httpclient-4.5.5.jar&lt;/span&gt;&lt;br/&gt;&lt;span class="meta"&gt;classpath: C:\Users\gaguilar\.m2\repository\org\apache\httpcomponents\httpcore\4.4.9\httpcore-4.4.9.jar&lt;/span&gt;&lt;br/&gt;&lt;span class="meta"&gt;classpath: C:\Users\gaguilar\.m2\repository\com\squareup\okhttp3\okhttp\3.10.0\okhttp-3.10.0.jar&lt;/span&gt;&lt;br/&gt;&lt;span class="meta"&gt;classpath: C:\Users\gaguilar\.m2\repository\com\squareup\okio\okio\1.14.1\okio-1.14.1.jar&lt;/span&gt;&lt;br/&gt;&lt;span class="meta"&gt;classpath: C:\Users\gaguilar\.m2\repository\commons-io\commons-io\2.6\commons-io-2.6.jar&lt;/span&gt;&lt;br/&gt;&lt;span class="meta"&gt;classpath: C:\Users\gaguilar\.m2\repository\org\fitnesse\fitnesse\20180127\fitnesse-20180127.jar&lt;/span&gt;&lt;br/&gt;&lt;span class="meta"&gt;classpath: C:\Users\gaguilar\.m2\repository\org\htmlparser\htmlparser\2.1\htmlparser-2.1.jar&lt;/span&gt;&lt;br/&gt;&lt;span class="meta"&gt;classpath: C:\Users\gaguilar\.m2\repository\org\htmlparser\htmllexer\2.1\htmllexer-2.1.jar&lt;/span&gt;&lt;br/&gt;&lt;span class="meta"&gt;classpath: C:\Users\gaguilar\.m2\repository\org\apache\velocity\velocity\1.7\velocity-1.7.jar&lt;/span&gt;&lt;br/&gt;&lt;span class="meta"&gt;classpath: C:\Users\gaguilar\.m2\repository\commons-lang\commons-lang\2.6\commons-lang-2.6.jar&lt;/span&gt;&lt;br/&gt;&lt;span class="meta"&gt;classpath: C:\Users\gaguilar\.m2\repository\commons-collections\commons-collections\3.2.2\commons-collections-3.2.2.jar&lt;/span&gt;&lt;br/&gt;&lt;span class="meta"&gt;classpath: C:\Users\gaguilar\.m2\repository\org\json\json\20151123\json-20151123.jar&lt;/span&gt;&lt;br/&gt;&lt;span class="meta"&gt;classpath: C:\Users\gaguilar\.m2\repository\com\googlecode\java-diff-utils\diffutils\1.3.0\diffutils-1.3.0.jar&lt;/span&gt;&lt;br/&gt;&lt;span class="meta"&gt;classpath: C:\Users\gaguilar\.m2\repository\org\apache\ant\ant\1.9.6\ant-1.9.6.jar&lt;/span&gt;&lt;br/&gt;&lt;span class="meta"&gt;classpath: C:\Users\gaguilar\.m2\repository\org\apache\ant\ant-launcher\1.9.6\ant-launcher-1.9.6.jar&lt;/span&gt;&lt;br/&gt;&lt;span class="meta"&gt;classpath: C:\Users\gaguilar\.m2\repository\junit\junit\4.12\junit-4.12.jar&lt;/span&gt;&lt;br/&gt;&lt;span class="meta"&gt;classpath: C:\Users\gaguilar\.m2\repository\org\hamcrest\hamcrest-core\1.3\hamcrest-core-1.3.jar&lt;/span&gt;&lt;br/&gt;&lt;span class="meta"&gt;classpath: C:\Users\gaguilar\.m2\repository\org\apache\poi\poi\3.11\poi-3.11.jar&lt;/span&gt;&lt;br/&gt;&lt;span class="meta"&gt;classpath: C:\Users\gaguilar\.m2\repository\org\apache\poi\poi-ooxml\3.11\poi-ooxml-3.11.jar&lt;/span&gt;&lt;br/&gt;&lt;span class="meta"&gt;classpath: C:\Users\gaguilar\.m2\repository\org\apache\poi\poi-ooxml-schemas\3.11\poi-ooxml-schemas-3.11.jar&lt;/span&gt;&lt;br/&gt;&lt;span class="meta"&gt;classpath: C:\Users\gaguilar\.m2\repository\org\apache\xmlbeans\xmlbeans\2.6.0\xmlbeans-2.6.0.jar&lt;/span&gt;&lt;br/&gt;&lt;span class="meta"&gt;classpath: C:\Users\gaguilar\.m2\repository\stax\stax-api\1.0.1\stax-api-1.0.1.jar&lt;/span&gt;&lt;br/&gt;&lt;span class="meta"&gt;classpath: C:\Users\gaguilar\.m2\repository\com\google\guava\guava\23.0\guava-23.0.jar&lt;/span&gt;&lt;br/&gt;&lt;span class="meta"&gt;classpath: C:\Users\gaguilar\.m2\repository\com\google\code\findbugs\jsr305\1.3.9\jsr305-1.3.9.jar&lt;/span&gt;&lt;br/&gt;&lt;span class="meta"&gt;classpath: C:\Users\gaguilar\.m2\repository\com\google\errorprone\error_prone_annotations\2.0.18\error_prone_annotations-2.0.18.jar&lt;/span&gt;&lt;br/&gt;&lt;span class="meta"&gt;classpath: C:\Users\gaguilar\.m2\repository\com\google\j2objc\j2objc-annotations\1.1\j2objc-annotations-1.1.jar&lt;/span&gt;&lt;br/&gt;&lt;span class="meta"&gt;classpath: C:\Users\gaguilar\.m2\repository\org\codehaus\mojo\animal-sniffer-annotations\1.14\animal-sniffer-annotations-1.14.jar&lt;/span&gt;&lt;br/&gt;&lt;span class="meta"&gt;classpath: C:\Users\gaguilar\.m2\repository\com\google\code\gson\gson\2.8.2\gson-2.8.2.jar&lt;/span&gt;&lt;br/&gt;&lt;span class="meta"&gt;classpath: C:\Users\gaguilar\.m2\repository\com\github\stephenc\monte\monte-screen-recorder\0.7.7.0\monte-screen-recorder-0.7.7.0.jar&lt;/span&gt;&lt;br/&gt;&lt;span class="meta"&gt;classpath: C:\Users\gaguilar\.m2\repository\uk\co\caprica\vlcj\3.10.1\vlcj-3.10.1.jar&lt;/span&gt;&lt;br/&gt;&lt;span class="meta"&gt;classpath: C:\Users\gaguilar\.m2\repository\net\java\dev\jna\jna-platform\4.1.0\jna-platform-4.1.0.jar&lt;/span&gt;&lt;br/&gt;&lt;span class="meta"&gt;classpath: C:\Users\gaguilar\.m2\repository\net\java\dev\jna\jna\4.2.0\jna-4.2.0.jar&lt;/span&gt;&lt;br/&gt;&lt;span class="meta"&gt;classpath: C:\Users\gaguilar\.m2\repository\org\slf4j\slf4j-api\1.7.25\slf4j-api-1.7.25.jar&lt;/span&gt;&lt;br/&gt;&lt;span class="meta"&gt;classpath: C:\Users\gaguilar\.m2\repository\org\slf4j\slf4j-log4j12\1.7.25\slf4j-log4j12-1.7.25.jar&lt;/span&gt;&lt;br/&gt;&lt;span class="meta"&gt;classpath: C:\Users\gaguilar\.m2\repository\log4j\log4j\1.2.17\log4j-1.2.17.jar&lt;/span&gt;&lt;br/&gt;&lt;span class="meta"&gt;classpath: C:\Users\gaguilar\.m2\repository\org\apache\logging\log4j\log4j-api\2.9.1\log4j-api-2.9.1.jar&lt;/span&gt;&lt;br/&gt;&lt;span class="meta"&gt;classpath: C:\Users\gaguilar\.m2\repository\org\apache\logging\log4j\log4j-core\2.9.1\log4j-core-2.9.1.jar&lt;/span&gt;&lt;br/&gt;&lt;span class="meta"&gt;classpath: C:\Users\gaguilar\.m2\repository\uk\co\caprica\vlcj\3.10.1\vlcj-3.10.1.jar&lt;/span&gt;&lt;br/&gt;&lt;/div&gt;
&lt;/div&gt;
&lt;div class="collapsible closed"&gt;&lt;ul&gt;&lt;li&gt;&lt;a href='#' class='expandall'&gt;Expand&lt;/a&gt;&lt;/li&gt;&lt;li&gt;&lt;a href='#' class='collapseall'&gt;Collapse&lt;/a&gt;&lt;/li&gt;&lt;/ul&gt;
	&lt;p class="title"&gt;imports&lt;/p&gt;
	&lt;div&gt;&lt;br/&gt;&lt;table&gt;
	&lt;tr class="slimRowTitle"&gt;
		&lt;td&gt;import&lt;/td&gt;
	&lt;/tr&gt;
	&lt;tr class="slimRowColor0"&gt;
		&lt;td&gt;&lt;span class="pass"&gt;configAutomation&lt;/span&gt;&lt;/td&gt;
	&lt;/tr&gt;
&lt;/table&gt;
&lt;br/&gt;&lt;table&gt;
	&lt;tr class="slimRowTitle"&gt;
		&lt;td&gt;import&lt;/td&gt;
	&lt;/tr&gt;
	&lt;tr class="slimRowColor0"&gt;
		&lt;td&gt;&lt;span class="pass"&gt;fitnesse.slim.test&lt;/span&gt;&lt;/td&gt;
	&lt;/tr&gt;
&lt;/table&gt;
&lt;br/&gt;&lt;table&gt;
	&lt;tr class="slimRowTitle"&gt;
		&lt;td&gt;import&lt;/td&gt;
	&lt;/tr&gt;
	&lt;tr class="slimRowColor0"&gt;
		&lt;td&gt;&lt;span class="pass"&gt;fitnesse.fixtures&lt;/span&gt;&lt;/td&gt;
	&lt;/tr&gt;
&lt;/table&gt;
&lt;/div&gt;
&lt;/div&gt;
&lt;br/&gt;</content>
    <relativePageName>TestFixture</relativePageName>
            <instructions>
            <instructionResult>
        <instruction>{id='import_0_0', instruction='import', path='configAutomation'}</instruction>
        <slimResult>pass(configAutomation)</slimResult>
                <expectation>
                    <status>pass</status>
                    <instructionId>import_0_0</instructionId>
                    <col>0</col>
                              <row>1</row>
                    <type>ImportExpectation</type>
                                        <evaluationMessage>configAutomation</evaluationMessage>
                  </expectation>
              </instructionResult>
            <instructionResult>
        <instruction>{id='import_1_0', instruction='import', path='fitnesse.slim.test'}</instruction>
        <slimResult>pass(fitnesse.slim.test)</slimResult>
                <expectation>
                    <status>pass</status>
                    <instructionId>import_1_0</instructionId>
                    <col>0</col>
                              <row>1</row>
                    <type>ImportExpectation</type>
                                        <evaluationMessage>fitnesse.slim.test</evaluationMessage>
                  </expectation>
              </instructionResult>
            <instructionResult>
        <instruction>{id='import_2_0', instruction='import', path='fitnesse.fixtures'}</instruction>
        <slimResult>pass(fitnesse.fixtures)</slimResult>
                <expectation>
                    <status>pass</status>
                    <instructionId>import_2_0</instructionId>
                    <col>0</col>
                              <row>1</row>
                    <type>ImportExpectation</type>
                                        <evaluationMessage>fitnesse.fixtures</evaluationMessage>
                  </expectation>
              </instructionResult>
          </instructions>
      </result>
  <executionLog>
    <testSystem>slim:fitnesse.slim.SlimService</testSystem>
    <command>"C:\Program Files\Java\jdk1.8.0_161\bin\java" -cp "C:\Users\gaguilar\.m2\repository\org\fitnesse\fitnesse\20180127\fitnesse-20180127.jar;C:\eclipse-workspace\configAutomation\target\classes;C:\baseline;C:\Program Files\Java\jre1.8.0_161\lib\resources.jar;C:\Program Files\Java\jre1.8.0_161\lib\rt.jar;C:\Program Files\Java\jre1.8.0_161\lib\jsse.jar;C:\Program Files\Java\jre1.8.0_161\lib\jce.jar;C:\Program Files\Java\jre1.8.0_161\lib\charsets.jar;C:\Program Files\Java\jre1.8.0_161\lib\jfr.jar;C:\Program Files\Java\jre1.8.0_161\lib\ext\access-bridge-64.jar;C:\Program Files\Java\jre1.8.0_161\lib\ext\cldrdata.jar;C:\Program Files\Java\jre1.8.0_161\lib\ext\dnsns.jar;C:\Program Files\Java\jre1.8.0_161\lib\ext\jaccess.jar;C:\Program Files\Java\jre1.8.0_161\lib\ext\jfxrt.jar;C:\Program Files\Java\jre1.8.0_161\lib\ext\localedata.jar;C:\Program Files\Java\jre1.8.0_161\lib\ext\nashorn.jar;C:\Program Files\Java\jre1.8.0_161\lib\ext\sunec.jar;C:\Program Files\Java\jre1.8.0_161\lib\ext\sunjce_provider.jar;C:\Program Files\Java\jre1.8.0_161\lib\ext\sunmscapi.jar;C:\Program Files\Java\jre1.8.0_161\lib\ext\sunpkcs11.jar;C:\Program Files\Java\jre1.8.0_161\lib\ext\zipfs.jar;C:\Users\gaguilar\.m2\repository\org\seleniumhq\selenium\selenium-java\3.14.0\selenium-java-3.14.0.jar;C:\Users\gaguilar\.m2\repository\org\seleniumhq\selenium\selenium-api\3.14.0\selenium-api-3.14.0.jar;C:\Users\gaguilar\.m2\repository\org\seleniumhq\selenium\selenium-edge-driver\3.14.0\selenium-edge-driver-3.14.0.jar;C:\Users\gaguilar\.m2\repository\org\seleniumhq\selenium\selenium-firefox-driver\3.14.0\selenium-firefox-driver-3.14.0.jar;C:\Users\gaguilar\.m2\repository\org\seleniumhq\selenium\selenium-ie-driver\3.14.0\selenium-ie-driver-3.14.0.jar;C:\Users\gaguilar\.m2\repository\org\seleniumhq\selenium\selenium-opera-driver\3.14.0\selenium-opera-driver-3.14.0.jar;C:\Users\gaguilar\.m2\repository\org\seleniumhq\selenium\selenium-remote-driver\3.14.0\selenium-remote-driver-3.14.0.jar;C:\Users\gaguilar\.m2\repository\org\seleniumhq\selenium\selenium-safari-driver\3.14.0\selenium-safari-driver-3.14.0.jar;C:\Users\gaguilar\.m2\repository\org\seleniumhq\selenium\selenium-support\3.14.0\selenium-support-3.14.0.jar;C:\Users\gaguilar\.m2\repository\org\seleniumhq\selenium\selenium-chrome-driver\3.14.0\selenium-chrome-driver-3.14.0.jar;C:\Users\gaguilar\.m2\repository\net\bytebuddy\byte-buddy\1.8.3\byte-buddy-1.8.3.jar;C:\Users\gaguilar\.m2\repository\org\apache\commons\commons-exec\1.3\commons-exec-1.3.jar;C:\Users\gaguilar\.m2\repository\commons-codec\commons-codec\1.10\commons-codec-1.10.jar;C:\Users\gaguilar\.m2\repository\commons-logging\commons-logging\1.2\commons-logging-1.2.jar;C:\Users\gaguilar\.m2\repository\org\apache\httpcomponents\httpclient\4.5.5\httpclient-4.5.5.jar;C:\Users\gaguilar\.m2\repository\org\apache\httpcomponents\httpcore\4.4.9\httpcore-4.4.9.jar;C:\Users\gaguilar\.m2\repository\com\squareup\okhttp3\okhttp\3.10.0\okhttp-3.10.0.jar;C:\Users\gaguilar\.m2\repository\com\squareup\okio\okio\1.14.1\okio-1.14.1.jar;C:\Users\gaguilar\.m2\repository\commons-io\commons-io\2.6\commons-io-2.6.jar;C:\Users\gaguilar\.m2\repository\org\fitnesse\fitnesse\20180127\fitnesse-20180127.jar;C:\Users\gaguilar\.m2\repository\org\htmlparser\htmlparser\2.1\htmlparser-2.1.jar;C:\Users\gaguilar\.m2\repository\org\htmlparser\htmllexer\2.1\htmllexer-2.1.jar;C:\Users\gaguilar\.m2\repository\org\apache\velocity\velocity\1.7\velocity-1.7.jar;C:\Users\gaguilar\.m2\repository\commons-lang\commons-lang\2.6\commons-lang-2.6.jar;C:\Users\gaguilar\.m2\repository\commons-collections\commons-collections\3.2.2\commons-collections-3.2.2.jar;C:\Users\gaguilar\.m2\repository\org\json\json\20151123\json-20151123.jar;C:\Users\gaguilar\.m2\repository\com\googlecode\java-diff-utils\diffutils\1.3.0\diffutils-1.3.0.jar;C:\Users\gaguilar\.m2\repository\org\apache\ant\ant\1.9.6\ant-1.9.6.jar;C:\Users\gaguilar\.m2\repository\org\apache\ant\ant-launcher\1.9.6\ant-launcher-1.9.6.jar;C:\Users\gaguilar\.m2\repository\junit\junit\4.12\junit-4.12.jar;C:\Users\gaguilar\.m2\repository\org\hamcrest\hamcrest-core\1.3\hamcrest-core-1.3.jar;C:\Users\gaguilar\.m2\repository\org\apache\poi\poi\3.11\poi-3.11.jar;C:\Users\gaguilar\.m2\repository\org\apache\poi\poi-ooxml\3.11\poi-ooxml-3.11.jar;C:\Users\gaguilar\.m2\repository\org\apache\poi\poi-ooxml-schemas\3.11\poi-ooxml-schemas-3.11.jar;C:\Users\gaguilar\.m2\repository\org\apache\xmlbeans\xmlbeans\2.6.0\xmlbeans-2.6.0.jar;C:\Users\gaguilar\.m2\repository\stax\stax-api\1.0.1\stax-api-1.0.1.jar;C:\Users\gaguilar\.m2\repository\com\google\guava\guava\23.0\guava-23.0.jar;C:\Users\gaguilar\.m2\repository\com\google\code\findbugs\jsr305\1.3.9\jsr305-1.3.9.jar;C:\Users\gaguilar\.m2\repository\com\google\errorprone\error_prone_annotations\2.0.18\error_prone_annotations-2.0.18.jar;C:\Users\gaguilar\.m2\repository\com\google\j2objc\j2objc-annotations\1.1\j2objc-annotations-1.1.jar;C:\Users\gaguilar\.m2\repository\org\codehaus\mojo\animal-sniffer-annotations\1.14\animal-sniffer-annotations-1.14.jar;C:\Users\gaguilar\.m2\repository\com\google\code\gson\gson\2.8.2\gson-2.8.2.jar;C:\Users\gaguilar\.m2\repository\com\github\stephenc\monte\monte-screen-recorder\0.7.7.0\monte-screen-recorder-0.7.7.0.jar;C:\Users\gaguilar\.m2\repository\uk\co\caprica\vlcj\3.10.1\vlcj-3.10.1.jar;C:\Users\gaguilar\.m2\repository\net\java\dev\jna\jna-platform\4.1.0\jna-platform-4.1.0.jar;C:\Users\gaguilar\.m2\repository\net\java\dev\jna\jna\4.2.0\jna-4.2.0.jar;C:\Users\gaguilar\.m2\repository\org\slf4j\slf4j-api\1.7.25\slf4j-api-1.7.25.jar;C:\Users\gaguilar\.m2\repository\org\slf4j\slf4j-log4j12\1.7.25\slf4j-log4j12-1.7.25.jar;C:\Users\gaguilar\.m2\repository\log4j\log4j\1.2.17\log4j-1.2.17.jar;C:\Users\gaguilar\.m2\repository\org\apache\logging\log4j\log4j-api\2.9.1\log4j-api-2.9.1.jar;C:\Users\gaguilar\.m2\repository\org\apache\logging\log4j\log4j-core\2.9.1\log4j-core-2.9.1.jar" fitnesse.slim.SlimService 1</command>
    <exitCode>1</exitCode>
    <stdOut></stdOut>
    <stdErr></stdErr>
    <exception>Index: 1, Size: 1</exception>
    <exception>java.lang.IndexOutOfBoundsException: Index: 1, Size: 1</exception>
  </executionLog>
  <finalCounts>
    <right>0</right>
    <wrong>0</wrong>
    <ignores>0</ignores>
    <exceptions>1</exceptions>
  </finalCounts>
  <totalRunTimeInMillis>1066</totalRunTimeInMillis>
</testResults>

